cricket/__init__.py
ckm-0.1.dist-info/METADATA
ckm-0.1.dist-info/WHEEL
ckm-0.1.dist-info/license.txt
ckm-0.1.dist-info/top_level.txt
ckm-0.1.dist-info/RECORD
