Metadata-Version: 2.1
Name: ckm
Version: 0.1
Summary: A very basic calculator
Author: Anusha H S
Author-email: anusha.anu.sam@gmail.com
Keywords: calculator
License-File: license.txt
